voltronsecurity/__init__.py
voltronsecurity/voltron_base.py
voltronsecurity-0.0.1.dist-info/LICENSE
voltronsecurity-0.0.1.dist-info/METADATA
voltronsecurity-0.0.1.dist-info/WHEEL
voltronsecurity-0.0.1.dist-info/top_level.txt
voltronsecurity-0.0.1.dist-info/RECORD
