Metadata-Version: 2.1
Name: voltronsecurity
Version: 0.0.1
Summary: Framework for Abstracting and Storing Security findings
Author-email: Matt Domko <hashtagcyber@users.noreply.github.com>
Classifier: Programming Language :: Python :: 3
Classifier: Operating System :: OS Independent
Classifier: License :: OSI Approved :: MIT License
Requires-Python: >=3.7
License-File: LICENSE
